topsis_package/__init__.py
topsis_package/__main__.py
Topsis_Parth_102203636-1.0.0.dist-info/LICENSE
Topsis_Parth_102203636-1.0.0.dist-info/METADATA
Topsis_Parth_102203636-1.0.0.dist-info/WHEEL
Topsis_Parth_102203636-1.0.0.dist-info/entry_points.txt
Topsis_Parth_102203636-1.0.0.dist-info/top_level.txt
Topsis_Parth_102203636-1.0.0.dist-info/RECORD
